dworm/__init__.py
dworm/asgi.py
dworm/dbrouter.py
dworm/settings.py
dworm/urls.py
dworm/wsgi.py
dworm/abc/BasicalMeta.py
dworm/abc/DataQuality.py
dworm/abc/MedicineMeta.py
dworm/abc/README.md
dworm/abc/__init__.py
dworm/abc/meta_abc.py
dworm/abc/meta_medicine.py
dworm/board/README.md
dworm/board/__init__.py
dworm/board/admin.py
dworm/board/apps.py
dworm/board/models.py
dworm/board/model/DqaModel.py
dworm/board/model/__init__.py
dworm/collection/README.md
dworm/collection/__init__.py
dworm/collection/admin.py
dworm/collection/apps.py
dworm/collection/models.py
dworm/collection/migrations/0001_initial.py
dworm/collection/migrations/0002_auto_20200225_1740.py
dworm/collection/migrations/0003_auto_20200225_1741.py
dworm/collection/migrations/0004_auto_20200226_1533.py
dworm/collection/migrations/0005_auto_20200226_1618.py
dworm/collection/migrations/__init__.py
dworm/collection/model/AiDiagnosis.py
dworm/collection/model/DCM.py
dworm/collection/model/Medicine315.py
dworm/collection/model/MedicineBase.py
dworm/collection/model/MedicineBbf.py
dworm/collection/model/MedicineChangping.py
dworm/collection/model/MedicineHayao.py
dworm/collection/model/MedicineKzj.py
dworm/collection/model/__init__.py
dworm/dqa/README.md
dworm/dqa/__init__.py
dworm/dqa/models.py
dworm/dqa/migrations/0001_initial.py
dworm/dqa/migrations/__init__.py
dworm/meta/BasicalMeta.py
dworm/meta/DataQuality.py
dworm/meta/MedicineMeta.py
dworm/meta/__init__.py
dworm/middle/README.md
dworm/middle/__init__.py
dworm/middle/admin.py
dworm/middle/apps.py
dworm/middle/models.py
dworm/middle/migrations/0001_initial.py
dworm/middle/migrations/__init__.py
dworm/middle/model/MiddleMedicine.py
dworm/middle/model/__init__.py
dworm/middle/model/medicine.py
dworm/middle/model/middle
dworm/topic/Checklist.py
dworm/topic/Diseases.py
dworm/topic/Hospital.py
dworm/topic/Medicine.py
dworm/topic/README.md
dworm/topic/__init__.py
dworm/topic/admin.py
dworm/topic/apps.py
dworm/topic/models.py
dworm-0.2.1.dist-info/AUTHORS
dworm-0.2.1.dist-info/METADATA
dworm-0.2.1.dist-info/WHEEL
dworm-0.2.1.dist-info/pbr.json
dworm-0.2.1.dist-info/top_level.txt
dworm-0.2.1.dist-info/RECORD
