Metadata-Version: 2.1
Name: dworm
Version: 0.2.1
Summary: data warehouse orms.
Home-page: http://example.com
Author: singein
Author-email: singein@outlook.com
License: MIT
Platform: UNKNOWN
